uci_cbp_demo/__init__.py
uci_cbp_demo/cli.py
uci_cbp_demo/backend/__init__.py
uci_cbp_demo/backend/data_export.py
uci_cbp_demo/backend/datastructures.py
uci_cbp_demo/backend/sensor_board.py
uci_cbp_demo/backend/bluetooth/__init__.py
uci_cbp_demo/backend/bluetooth/callbacks.py
uci_cbp_demo/backend/bluetooth/constants.py
uci_cbp_demo/backend/bluetooth/list_characteristics.py
uci_cbp_demo/backend/bluetooth/scan.py
uci_cbp_demo/backend/bluetooth/utils.py
uci_cbp_demo/config/__init__.py
uci_cbp_demo/config/configuration.py
uci_cbp_demo/logging/__init__.py
uci_cbp_demo/logging/logger.py
uci_cbp_demo/ui/__init__.py
uci_cbp_demo/ui/gui.py
uci_cbp_demo/ui/terminal.py
uci_cbp_demo/ui/tui.py
uci_cbp_demo/ui/widget_about.py
uci_cbp_demo/ui/widget_canvas.py
uci_cbp_demo/ui/widget_dac_control.py
uci_cbp_demo/ui/widget_preferences.py
uci_cbp_demo/ui/widget_scan.py
uci_cbp_demo-0.6.0.dist-info/AUTHORS.rst
uci_cbp_demo-0.6.0.dist-info/LICENSE
uci_cbp_demo-0.6.0.dist-info/METADATA
uci_cbp_demo-0.6.0.dist-info/WHEEL
uci_cbp_demo-0.6.0.dist-info/entry_points.txt
uci_cbp_demo-0.6.0.dist-info/top_level.txt
uci_cbp_demo-0.6.0.dist-info/RECORD
