Metadata-Version: 2.1
Name: uci-cbp-demo
Version: 0.6.0
Summary: GUI to demo continuous blood pressure sensing
Home-page: https://github.com/taoyilee/bp_demo
Author: UCI cBP demo
Author-email: taoyil@uci.edu
License: MIT license
Keywords: uci_cbp_demo
Platform: UNKNOWN
Classifier: Development Status :: 2 - Pre-Alpha
Classifier: Intended Audience :: Developers
Classifier: License :: OSI Approved :: MIT License
Classifier: Natural Language :: English
Classifier: Programming Language :: Python :: 3.6
Classifier: Programming Language :: Python :: 3.7
Classifier: Programming Language :: Python :: 3.8
Requires-Python: >=3.6
Requires-Dist: Click (>=7.0)
Requires-Dist: numpy (==1.18.1)
Requires-Dist: matplotlib (==3.2.1)
Requires-Dist: configobj (==5.0.6)
Requires-Dist: appdirs (==1.4.3)
Requires-Dist: scipy (==1.4.1)
Requires-Dist: bleak (==0.6.1)
Requires-Dist: pandas (==1.0.3)
